calculator_bladda/__init__.py
calculator_bladda/calc_bladda.py
calculator_bladda-0.0.1.dist-info/LICENSE
calculator_bladda-0.0.1.dist-info/WHEEL
calculator_bladda-0.0.1.dist-info/METADATA
calculator_bladda-0.0.1.dist-info/RECORD
