Metadata-Version: 2.1
Name: calculator_bladda
Version: 0.0.1
Summary: Calculator package by Adda Blaise
Author-email: Adda Blaise <addablaise@gmail.com>
Classifier: License :: OSI Approved :: MIT License
